Workbook

Sheet Q1
B2: Q1) Instructions
B3: Calculate Net Operating Income and create a dynamic model that updates based on the holding period of 2-10y. Assume no sale proceeds at the end of the holding period.
B5: Assumptions | G5: {=IF(SUM(IF(D25:M32,1))=80,"R","T")} -> T
B6: Rental Income Growth Rate | C6: 0.035
B7: R&M as a % of Rev. | C7: 0.096
B8: Utilities as a % of Rev. | C8: 0.078
B9: Mgmt. Fees as a % of Rev. | C9: 0.044
B11: Holding Period → | D11: ← Create Dropdown List
C13: Holding Period
D14: =C14+1 -> 1 | E14: =D14+1 -> 2 | F14: =E14+1 -> 3 | G14: =F14+1 -> 4 | H14: =G14+1 -> 5 | I14: =H14+1 -> 6 | J14: =I14+1 -> 7 | K14: =J14+1 -> 8 | ... M14: =L14+1 -> 10
B15: Revenue:
B16: Rental Income | D16: 55995
B17: Total Revenue
B18: Operating Expenses:
B19: Repairs & Maintenance
B20: Utilities
B21: Management fees
B22: Total Operating Expenses
B23: Net Operating Income
D25: =D16='A1'!D16 -> TRUE | E25: =E16='A1'!E16 -> TRUE | F25: =F16='A1'!F16 -> TRUE | G25: =G16='A1'!G16 -> TRUE | H25: =H16='A1'!H16 -> TRUE | I25: =I16='A1'!I16 -> TRUE | J25: =J16='A1'!J16 -> TRUE | K25: =K16='A1'!K16 -> TRUE | ... M25: =M16='A1'!M16 -> TRUE
D26: =D17='A1'!D17 -> TRUE | E26: =E17='A1'!E17 -> TRUE | F26: =F17='A1'!F17 -> TRUE | G26: =G17='A1'!G17 -> TRUE | H26: =H17='A1'!H17 -> TRUE | I26: =I17='A1'!I17 -> TRUE | J26: =J17='A1'!J17 -> TRUE | K26: =K17='A1'!K17 -> TRUE | ... M26: =M17='A1'!M17 -> TRUE
D27: =D18='A1'!D18 -> TRUE | E27: =E18='A1'!E18 -> TRUE | F27: =F18='A1'!F18 -> TRUE | G27: =G18='A1'!G18 -> TRUE | H27: =H18='A1'!H18 -> TRUE | I27: =I18='A1'!I18 -> TRUE | J27: =J18='A1'!J18 -> TRUE | K27: =K18='A1'!K18 -> TRUE | ... M27: =M18='A1'!M18 -> TRUE
D28: =D19='A1'!D19 -> FALSE | E28: =E19='A1'!E19 -> TRUE | F28: =F19='A1'!F19 -> TRUE | G28: =G19='A1'!G19 -> TRUE | H28: =H19='A1'!H19 -> TRUE | I28: =I19='A1'!I19 -> TRUE | J28: =J19='A1'!J19 -> TRUE | K28: =K19='A1'!K19 -> TRUE | ... M28: =M19='A1'!M19 -> TRUE
D29: =D20='A1'!D20 -> FALSE | E29: =E20='A1'!E20 -> TRUE | F29: =F20='A1'!F20 -> TRUE | G29: =G20='A1'!G20 -> TRUE | H29: =H20='A1'!H20 -> TRUE | I29: =I20='A1'!I20 -> TRUE | J29: =J20='A1'!J20 -> TRUE | K29: =K20='A1'!K20 -> TRUE | ... M29: =M20='A1'!M20 -> TRUE
D30: =D21='A1'!D21 -> FALSE | E30: =E21='A1'!E21 -> TRUE | F30: =F21='A1'!F21 -> TRUE | G30: =G21='A1'!G21 -> TRUE | H30: =H21='A1'!H21 -> TRUE | I30: =I21='A1'!I21 -> TRUE | J30: =J21='A1'!J21 -> TRUE | K30: =K21='A1'!K21 -> TRUE | ... M30: =M21='A1'!M21 -> TRUE
D31: =D22='A1'!D22 -> FALSE | E31: =E22='A1'!E22 -> TRUE | F31: =F22='A1'!F22 -> TRUE | G31: =G22='A1'!G22 -> TRUE | H31: =H22='A1'!H22 -> TRUE | I31: =I22='A1'!I22 -> TRUE | J31: =J22='A1'!J22 -> TRUE | K31: =K22='A1'!K22 -> TRUE | ... M31: =M22='A1'!M22 -> TRUE
D32: =D23='A1'!D23 -> FALSE | E32: =E23='A1'!E23 -> TRUE | F32: =F23='A1'!F23 -> TRUE | G32: =G23='A1'!G23 -> TRUE | H32: =H23='A1'!H23 -> TRUE | I32: =I23='A1'!I23 -> TRUE | J32: =J23='A1'!J23 -> TRUE | K32: =K23='A1'!K23 -> TRUE | ... M32: =M23='A1'!M23 -> TRUE

Sheet Q2
B2: Q2) Instructions | L2: {=IF(AND(SUM(IF($L$15:$M$19,1))=10,SUM(IF($L$7:$M$11,1))=10),"R","T")} -> T
B3: Fill the tables to show the top 5 and bottom 5 brands by gross margin percentage
B5: Brand | C5: Revenue | D5: COGS | E5: Gross Margin | F5: Gross Margin % | H5: Top 5 Gross Margin %
B6: Coca-Cola | C6: 928221.04 | D6: 371488 | E6: =C6-D6 -> 556733.04 | F6: =E6/C6 -> 0.59978498 | H6: Rank | I6: Margin % | J6: Brand
B7: Diet Coke | C7: 710961.16 | D7: 641971.48 | E7: =C7-D7 -> 68989.68 | F7: =E7/C7 -> 0.097037199 | H7: 1 | L7: =I7='A2'!I7 -> FALSE | M7: =J7='A2'!J7 -> FALSE
B8: Sprite | C8: 464919.49 | D8: 188254.89 | E8: =C8-D8 -> 276664.6 | F8: =E8/C8 -> 0.59508066 | H8: 2 | L8: =I8='A2'!I8 -> FALSE | M8: =J8='A2'!J8 -> FALSE
B9: Fanta | C9: 654490.73 | D9: 331570.26 | E9: =C9-D9 -> 322920.47 | F9: =E9/C9 -> 0.49339197 | H9: 3 | L9: =I9='A2'!I9 -> FALSE | M9: =J9='A2'!J9 -> FALSE
B10: Vitamin Water | C10: 606331.7 | D10: 395368.37 | E10: =C10-D10 -> 210963.33 | F10: =E10/C10 -> 0.34793386 | H10: 4 | L10: =I10='A2'!I10 -> FALSE | M10: =J10='A2'!J10 -> FALSE
B11: Honest Tea | C11: 956480.4 | D11: 737076.41 | E11: =C11-D11 -> 219403.99 | F11: =E11/C11 -> 0.22938681 | H11: 5 | L11: =I11='A2'!I11 -> FALSE | M11: =J11='A2'!J11 -> FALSE
B12: Powerade | C12: 307894.79 | D12: 188970 | E12: =C12-D12 -> 118924.79 | F12: =E12/C12 -> 0.38625139
B13: Costa Coffee | C13: 277939 | D13: 112880 | E13: =C13-D13 -> 165059 | F13: =E13/C13 -> 0.59386772 | H13: Bottom 5 Gross Margin %
B14: Minute Maid | C14: 443867.62 | D14: 268369.35 | E14: =C14-D14 -> 175498.27 | F14: =E14/C14 -> 0.39538426 | H14: Rank | I14: Margin % | J14: Brand
B15: Peace Tea | C15: 146516.05 | D15: 85987 | E15: =C15-D15 -> 60529.054 | F15: =E15/C15 -> 0.41312233 | H15: 1 | L15: =I15='A2'!I15 -> FALSE | M15: =J15='A2'!J15 -> FALSE
B16: Georgia Coffee | C16: 468784.32 | D16: 414121.48 | E16: =C16-D16 -> 54662.838 | F16: =E16/C16 -> 0.11660552 | H16: 2 | L16: =I16='A2'!I16 -> FALSE | M16: =J16='A2'!J16 -> FALSE
B17: Aquarius | C17: 716204.31 | D17: 329969.38 | E17: =C17-D17 -> 386234.93 | F17: =E17/C17 -> 0.53928038 | H17: 3 | L17: =I17='A2'!I17 -> FALSE | M17: =J17='A2'!J17 -> FALSE
H18: 4 | L18: =I18='A2'!I18 -> FALSE | M18: =J18='A2'!J18 -> FALSE
H19: 5 | L19: =I19='A2'!I19 -> FALSE | M19: =J19='A2'!J19 -> FALSE

Sheet Q3
B2: Q3) Instructions
B3: Create a monthly salary expense table in the light blue area. Please consider prorated expense amounts given a specific resignation date
B5: Resignations | C5: Salary per month | D5: Resignation date | F5: 44562 | G5: =EDATE(F5,1) -> 44593 | H5: =EDATE(G5,1) -> 44621 | I5: =EDATE(H5,1) -> 44652 | J5: =EDATE(I5,1) -> 44682 | K5: =EDATE(J5,1) -> 44713 | L5: =EDATE(K5,1) -> 44743 | M5: =EDATE(L5,1) -> 44774 | N5: =EDATE(M5,1) -> 44805 | ... Q5: =EDATE(P5,1) -> 44896
B6: Research Analyst | C6: 5000 | D6: 44635
B7: Sr. Financial Analyst | C7: 7000 | D7: 44729
B8: Jr. Financial Analyst | C8: 5000 | D8: 44597
B9: HR Recruiter | C9: 4000 | D9: 44798
B10: Copywriter | C10: 3500 | D10: 44579
B12: {=IF(SUM(IF($L$15:$M$19,1))=60,"R","T")} -> T | F12: =F6='A3'!F6 -> FALSE | G12: =G6='A3'!G6 -> FALSE | H12: =H6='A3'!H6 -> FALSE | I12: =I6='A3'!I6 -> TRUE | J12: =J6='A3'!J6 -> TRUE | K12: =K6='A3'!K6 -> TRUE | L12: =L6='A3'!L6 -> TRUE | M12: =M6='A3'!M6 -> TRUE | ... Q12: =Q6='A3'!Q6 -> TRUE
F13: =F7='A3'!F7 -> FALSE | G13: =G7='A3'!G7 -> FALSE | H13: =H7='A3'!H7 -> FALSE | I13: =I7='A3'!I7 -> FALSE | J13: =J7='A3'!J7 -> FALSE | K13: =K7='A3'!K7 -> FALSE | L13: =L7='A3'!L7 -> TRUE | M13: =M7='A3'!M7 -> TRUE | ... Q13: =Q7='A3'!Q7 -> TRUE
F14: =F8='A3'!F8 -> FALSE | G14: =G8='A3'!G8 -> FALSE | H14: =H8='A3'!H8 -> TRUE | I14: =I8='A3'!I8 -> TRUE | J14: =J8='A3'!J8 -> TRUE | K14: =K8='A3'!K8 -> TRUE | L14: =L8='A3'!L8 -> TRUE | M14: =M8='A3'!M8 -> TRUE | ... Q14: =Q8='A3'!Q8 -> TRUE
F15: =F9='A3'!F9 -> FALSE | G15: =G9='A3'!G9 -> FALSE | H15: =H9='A3'!H9 -> FALSE | I15: =I9='A3'!I9 -> FALSE | J15: =J9='A3'!J9 -> FALSE | K15: =K9='A3'!K9 -> FALSE | L15: =L9='A3'!L9 -> FALSE | M15: =M9='A3'!M9 -> FALSE | ... Q15: =Q9='A3'!Q9 -> TRUE
F16: =F10='A3'!F10 -> FALSE | G16: =G10='A3'!G10 -> TRUE | H16: =H10='A3'!H10 -> TRUE | I16: =I10='A3'!I10 -> TRUE | J16: =J10='A3'!J10 -> TRUE | K16: =K10='A3'!K10 -> TRUE | L16: =L10='A3'!L10 -> TRUE | M16: =M10='A3'!M10 -> TRUE | ... Q16: =Q10='A3'!Q10 -> TRUE

Sheet A1
B2: Q1) Instructions
B3: Calculate Net Operating Income and create a dynamic model that updates based on the holding period of 2-10y. Assume no sale proceeds at the end of the holding period.
B5: Assumptions
B6: Rental Income Growth Rate | C6: 0.035
B7: R&M as a % of Rev. | C7: 0.096
B8: Utilities as a % of Rev. | C8: 0.078
B9: Mgmt. Fees as a % of Rev. | C9: 0.044
C13: Holding Period
D14: =C14+1 -> 1 | E14: =D14+1 -> 2 | F14: =E14+1 -> 3 | G14: =F14+1 -> 4 | H14: =G14+1 -> 5 | I14: =H14+1 -> 6 | J14: =I14+1 -> 7 | K14: =J14+1 -> 8 | ... M14: =L14+1 -> 10
B15: Revenue:
B16: Rental Income | D16: 55995 | E16: =IF(E$14<='Q1'!$C$11,D16*$C$6+D16,0) -> 0 | F16: =IF(F$14<='Q1'!$C$11,E16*$C$6+E16,0) -> 0 | G16: =IF(G$14<='Q1'!$C$11,F16*$C$6+F16,0) -> 0 | H16: =IF(H$14<='Q1'!$C$11,G16*$C$6+G16,0) -> 0 | I16: =IF(I$14<='Q1'!$C$11,H16*$C$6+H16,0) -> 0 | J16: =IF(J$14<='Q1'!$C$11,I16*$C$6+I16,0) -> 0 | K16: =IF(K$14<='Q1'!$C$11,J16*$C$6+J16,0) -> 0 | L16: =IF(L$14<='Q1'!$C$11,K16*$C$6+K16,0) -> 0 | M16: =IF(M$14<='Q1'!$C$11,L16*$C$6+L16,0) -> 0
B17: Total Revenue
B18: Operating Expenses:
B19: Repairs & Maintenance | D19: =IFERROR($C7*D$16,0) -> 5375.52 | E19: =IFERROR($C7*E$16,0) -> 0 | F19: =IFERROR($C7*F$16,0) -> 0 | G19: =IFERROR($C7*G$16,0) -> 0 | H19: =IFERROR($C7*H$16,0) -> 0 | I19: =IFERROR($C7*I$16,0) -> 0 | J19: =IFERROR($C7*J$16,0) -> 0 | K19: =IFERROR($C7*K$16,0) -> 0 | ... M19: =IFERROR($C7*M$16,0) -> 0
B20: Utilities | D20: =IFERROR($C8*D$16,0) -> 4367.61 | E20: =IFERROR($C8*E$16,0) -> 0 | F20: =IFERROR($C8*F$16,0) -> 0 | G20: =IFERROR($C8*G$16,0) -> 0 | H20: =IFERROR($C8*H$16,0) -> 0 | I20: =IFERROR($C8*I$16,0) -> 0 | J20: =IFERROR($C8*J$16,0) -> 0 | K20: =IFERROR($C8*K$16,0) -> 0 | ... M20: =IFERROR($C8*M$16,0) -> 0
B21: Management fees | D21: =IFERROR($C9*D$16,0) -> 2463.78 | E21: =IFERROR($C9*E$16,0) -> 0 | F21: =IFERROR($C9*F$16,0) -> 0 | G21: =IFERROR($C9*G$16,0) -> 0 | H21: =IFERROR($C9*H$16,0) -> 0 | I21: =IFERROR($C9*I$16,0) -> 0 | J21: =IFERROR($C9*J$16,0) -> 0 | K21: =IFERROR($C9*K$16,0) -> 0 | ... M21: =IFERROR($C9*M$16,0) -> 0
B22: Total Operating Expenses | D22: =IFERROR(SUM(D19:D21),0) -> 12206.91 | E22: =IFERROR(SUM(E19:E21),0) -> 0 | F22: =IFERROR(SUM(F19:F21),0) -> 0 | G22: =IFERROR(SUM(G19:G21),0) -> 0 | H22: =IFERROR(SUM(H19:H21),0) -> 0 | I22: =IFERROR(SUM(I19:I21),0) -> 0 | J22: =IFERROR(SUM(J19:J21),0) -> 0 | K22: =IFERROR(SUM(K19:K21),0) -> 0 | ... M22: =IFERROR(SUM(M19:M21),0) -> 0
B23: Net Operating Income | D23: =IFERROR(D16-D22,0) -> 43788.09 | E23: =IFERROR(E16-E22,0) -> 0 | F23: =IFERROR(F16-F22,0) -> 0 | G23: =IFERROR(G16-G22,0) -> 0 | H23: =IFERROR(H16-H22,0) -> 0 | I23: =IFERROR(I16-I22,0) -> 0 | J23: =IFERROR(J16-J22,0) -> 0 | K23: =IFERROR(K16-K22,0) -> 0 | ... M23: =IFERROR(M16-M22,0) -> 0

Sheet A2
B2: Q2) Instructions
B3: Fill the tables to show the top 5 and bottom 5 brands by gross margin percentage
B5: Brand | C5: Revenue | D5: COGS | E5: Gross Margin | F5: Gross Margin % | H5: Top 5 Gross Margin %
B6: Coca-Cola | C6: 928221.04 | D6: 371488 | E6: =C6-D6 -> 556733.04 | F6: =E6/C6 -> 0.59978498 | H6: Rank | I6: Margin % | J6: Brand
B7: Diet Coke | C7: 710961.16 | D7: 641971.48 | E7: =C7-D7 -> 68989.68 | F7: =E7/C7 -> 0.097037199 | H7: 1 | I7: =LARGE($F$6:$F$17,H7) -> 0.59978498 | J7: =INDEX($B$6:$B$17,MATCH(I7,$F$6:$F$17,0)) -> Coca-Cola
B8: Sprite | C8: 464919.49 | D8: 188254.89 | E8: =C8-D8 -> 276664.6 | F8: =E8/C8 -> 0.59508066 | H8: 2 | I8: =LARGE($F$6:$F$17,H8) -> 0.59508066 | J8: =INDEX($B$6:$B$17,MATCH(I8,$F$6:$F$17,0)) -> Sprite
B9: Fanta | C9: 654490.73 | D9: 331570.26 | E9: =C9-D9 -> 322920.47 | F9: =E9/C9 -> 0.49339197 | H9: 3 | I9: =LARGE($F$6:$F$17,H9) -> 0.59386772 | J9: =INDEX($B$6:$B$17,MATCH(I9,$F$6:$F$17,0)) -> Costa Coffee
B10: Vitamin Water | C10: 606331.7 | D10: 395368.37 | E10: =C10-D10 -> 210963.33 | F10: =E10/C10 -> 0.34793386 | H10: 4 | I10: =LARGE($F$6:$F$17,H10) -> 0.53928038 | J10: =INDEX($B$6:$B$17,MATCH(I10,$F$6:$F$17,0)) -> Aquarius
B11: Honest Tea | C11: 956480.4 | D11: 737076.41 | E11: =C11-D11 -> 219403.99 | F11: =E11/C11 -> 0.22938681 | H11: 5 | I11: =LARGE($F$6:$F$17,H11) -> 0.49339197 | J11: =INDEX($B$6:$B$17,MATCH(I11,$F$6:$F$17,0)) -> Fanta
B12: Powerade | C12: 307894.79 | D12: 188970 | E12: =C12-D12 -> 118924.79 | F12: =E12/C12 -> 0.38625139
B13: Costa Coffee | C13: 277939 | D13: 112880 | E13: =C13-D13 -> 165059 | F13: =E13/C13 -> 0.59386772 | H13: Bottom 5 Gross Margin %
B14: Minute Maid | C14: 443867.62 | D14: 268369.35 | E14: =C14-D14 -> 175498.27 | F14: =E14/C14 -> 0.39538426 | H14: Rank | I14: Margin % | J14: Brand
B15: Peace Tea | C15: 146516.05 | D15: 85987 | E15: =C15-D15 -> 60529.054 | F15: =E15/C15 -> 0.41312233 | H15: 1 | I15: =SMALL($F$6:$F$17,H15) -> 0.097037199 | J15: =INDEX($B$6:$B$17,MATCH(I15,$F$6:$F$17,0)) -> Diet Coke
B16: Georgia Coffee | C16: 468784.32 | D16: 414121.48 | E16: =C16-D16 -> 54662.838 | F16: =E16/C16 -> 0.11660552 | H16: 2 | I16: =SMALL($F$6:$F$17,H16) -> 0.11660552 | J16: =INDEX($B$6:$B$17,MATCH(I16,$F$6:$F$17,0)) -> Georgia Coffee
B17: Aquarius | C17: 716204.31 | D17: 329969.38 | E17: =C17-D17 -> 386234.93 | F17: =E17/C17 -> 0.53928038 | H17: 3 | I17: =SMALL($F$6:$F$17,H17) -> 0.22938681 | J17: =INDEX($B$6:$B$17,MATCH(I17,$F$6:$F$17,0)) -> Honest Tea
H18: 4 | I18: =SMALL($F$6:$F$17,H18) -> 0.34793386 | J18: =INDEX($B$6:$B$17,MATCH(I18,$F$6:$F$17,0)) -> Vitamin Water
H19: 5 | I19: =SMALL($F$6:$F$17,H19) -> 0.38625139 | J19: =INDEX($B$6:$B$17,MATCH(I19,$F$6:$F$17,0)) -> Powerade

Sheet A3
B2: Q3) Instructions
B3: Create a monthly salary expense table in the light blue area. Please consider prorated expense amounts given a specific resignation date
B5: Resignations | C5: Salary per month | D5: Resignation date | F5: 44562 | G5: =EDATE(F5,1) -> 44593 | H5: =EDATE(G5,1) -> 44621 | I5: =EDATE(H5,1) -> 44652 | J5: =EDATE(I5,1) -> 44682 | K5: =EDATE(J5,1) -> 44713 | L5: =EDATE(K5,1) -> 44743 | M5: =EDATE(L5,1) -> 44774 | N5: =EDATE(M5,1) -> 44805 | ... Q5: =EDATE(P5,1) -> 44896
B6: Research Analyst | C6: 5000 | D6: 44635 | F6: =IF(MONTH(F$5)<MONTH($D6),$C6,IF(MONTH(F$5)=MONTH($D6),DAY($D6)/DAY(EOMONTH(F$5,0))*$C6,0)) -> 5000 | G6: =IF(MONTH(G$5)<MONTH($D6),$C6,IF(MONTH(G$5)=MONTH($D6),DAY($D6)/DAY(EOMONTH(G$5,0))*$C6,0)) -> 5000 | H6: =IF(MONTH(H$5)<MONTH($D6),$C6,IF(MONTH(H$5)=MONTH($D6),DAY($D6)/DAY(EOMONTH(H$5,0))*$C6,0)) -> 2419.3548 | I6: =IF(MONTH(I$5)<MONTH($D6),$C6,IF(MONTH(I$5)=MONTH($D6),DAY($D6)/DAY(EOMONTH(I$5,0))*$C6,0)) -> 0 | J6: =IF(MONTH(J$5)<MONTH($D6),$C6,IF(MONTH(J$5)=MONTH($D6),DAY($D6)/DAY(EOMONTH(J$5,0))*$C6,0)) -> 0 | K6: =IF(MONTH(K$5)<MONTH($D6),$C6,IF(MONTH(K$5)=MONTH($D6),DAY($D6)/DAY(EOMONTH(K$5,0))*$C6,0)) -> 0 | L6: =IF(MONTH(L$5)<MONTH($D6),$C6,IF(MONTH(L$5)=MONTH($D6),DAY($D6)/DAY(EOMONTH(L$5,0))*$C6,0)) -> 0 | M6: =IF(MONTH(M$5)<MONTH($D6),$C6,IF(MONTH(M$5)=MONTH($D6),DAY($D6)/DAY(EOMONTH(M$5,0))*$C6,0)) -> 0 | ... Q6: =IF(MONTH(Q$5)<MONTH($D6),$C6,IF(MONTH(Q$5)=MONTH($D6),DAY($D6)/DAY(EOMONTH(Q$5,0))*$C6,0)) -> 0
B7: Sr. Financial Analyst | C7: 7000 | D7: 44729 | F7: =IF(MONTH(F$5)<MONTH($D7),$C7,IF(MONTH(F$5)=MONTH($D7),DAY($D7)/DAY(EOMONTH(F$5,0))*$C7,0)) -> 7000 | G7: =IF(MONTH(G$5)<MONTH($D7),$C7,IF(MONTH(G$5)=MONTH($D7),DAY($D7)/DAY(EOMONTH(G$5,0))*$C7,0)) -> 7000 | H7: =IF(MONTH(H$5)<MONTH($D7),$C7,IF(MONTH(H$5)=MONTH($D7),DAY($D7)/DAY(EOMONTH(H$5,0))*$C7,0)) -> 7000 | I7: =IF(MONTH(I$5)<MONTH($D7),$C7,IF(MONTH(I$5)=MONTH($D7),DAY($D7)/DAY(EOMONTH(I$5,0))*$C7,0)) -> 7000 | J7: =IF(MONTH(J$5)<MONTH($D7),$C7,IF(MONTH(J$5)=MONTH($D7),DAY($D7)/DAY(EOMONTH(J$5,0))*$C7,0)) -> 7000 | K7: =IF(MONTH(K$5)<MONTH($D7),$C7,IF(MONTH(K$5)=MONTH($D7),DAY($D7)/DAY(EOMONTH(K$5,0))*$C7,0)) -> 3966.6667 | L7: =IF(MONTH(L$5)<MONTH($D7),$C7,IF(MONTH(L$5)=MONTH($D7),DAY($D7)/DAY(EOMONTH(L$5,0))*$C7,0)) -> 0 | M7: =IF(MONTH(M$5)<MONTH($D7),$C7,IF(MONTH(M$5)=MONTH($D7),DAY($D7)/DAY(EOMONTH(M$5,0))*$C7,0)) -> 0 | ... Q7: =IF(MONTH(Q$5)<MONTH($D7),$C7,IF(MONTH(Q$5)=MONTH($D7),DAY($D7)/DAY(EOMONTH(Q$5,0))*$C7,0)) -> 0
B8: Jr. Financial Analyst | C8: 5000 | D8: 44597 | F8: =IF(MONTH(F$5)<MONTH($D8),$C8,IF(MONTH(F$5)=MONTH($D8),DAY($D8)/DAY(EOMONTH(F$5,0))*$C8,0)) -> 5000 | G8: =IF(MONTH(G$5)<MONTH($D8),$C8,IF(MONTH(G$5)=MONTH($D8),DAY($D8)/DAY(EOMONTH(G$5,0))*$C8,0)) -> 892.85714 | H8: =IF(MONTH(H$5)<MONTH($D8),$C8,IF(MONTH(H$5)=MONTH($D8),DAY($D8)/DAY(EOMONTH(H$5,0))*$C8,0)) -> 0 | I8: =IF(MONTH(I$5)<MONTH($D8),$C8,IF(MONTH(I$5)=MONTH($D8),DAY($D8)/DAY(EOMONTH(I$5,0))*$C8,0)) -> 0 | J8: =IF(MONTH(J$5)<MONTH($D8),$C8,IF(MONTH(J$5)=MONTH($D8),DAY($D8)/DAY(EOMONTH(J$5,0))*$C8,0)) -> 0 | K8: =IF(MONTH(K$5)<MONTH($D8),$C8,IF(MONTH(K$5)=MONTH($D8),DAY($D8)/DAY(EOMONTH(K$5,0))*$C8,0)) -> 0 | L8: =IF(MONTH(L$5)<MONTH($D8),$C8,IF(MONTH(L$5)=MONTH($D8),DAY($D8)/DAY(EOMONTH(L$5,0))*$C8,0)) -> 0 | M8: =IF(MONTH(M$5)<MONTH($D8),$C8,IF(MONTH(M$5)=MONTH($D8),DAY($D8)/DAY(EOMONTH(M$5,0))*$C8,0)) -> 0 | ... Q8: =IF(MONTH(Q$5)<MONTH($D8),$C8,IF(MONTH(Q$5)=MONTH($D8),DAY($D8)/DAY(EOMONTH(Q$5,0))*$C8,0)) -> 0
B9: HR Recruiter | C9: 4000 | D9: 44798 | F9: =IF(MONTH(F$5)<MONTH($D9),$C9,IF(MONTH(F$5)=MONTH($D9),DAY($D9)/DAY(EOMONTH(F$5,0))*$C9,0)) -> 4000 | G9: =IF(MONTH(G$5)<MONTH($D9),$C9,IF(MONTH(G$5)=MONTH($D9),DAY($D9)/DAY(EOMONTH(G$5,0))*$C9,0)) -> 4000 | H9: =IF(MONTH(H$5)<MONTH($D9),$C9,IF(MONTH(H$5)=MONTH($D9),DAY($D9)/DAY(EOMONTH(H$5,0))*$C9,0)) -> 4000 | I9: =IF(MONTH(I$5)<MONTH($D9),$C9,IF(MONTH(I$5)=MONTH($D9),DAY($D9)/DAY(EOMONTH(I$5,0))*$C9,0)) -> 4000 | J9: =IF(MONTH(J$5)<MONTH($D9),$C9,IF(MONTH(J$5)=MONTH($D9),DAY($D9)/DAY(EOMONTH(J$5,0))*$C9,0)) -> 4000 | K9: =IF(MONTH(K$5)<MONTH($D9),$C9,IF(MONTH(K$5)=MONTH($D9),DAY($D9)/DAY(EOMONTH(K$5,0))*$C9,0)) -> 4000 | L9: =IF(MONTH(L$5)<MONTH($D9),$C9,IF(MONTH(L$5)=MONTH($D9),DAY($D9)/DAY(EOMONTH(L$5,0))*$C9,0)) -> 4000 | M9: =IF(MONTH(M$5)<MONTH($D9),$C9,IF(MONTH(M$5)=MONTH($D9),DAY($D9)/DAY(EOMONTH(M$5,0))*$C9,0)) -> 3225.8065 | ... Q9: =IF(MONTH(Q$5)<MONTH($D9),$C9,IF(MONTH(Q$5)=MONTH($D9),DAY($D9)/DAY(EOMONTH(Q$5,0))*$C9,0)) -> 0
B10: Copywriter | C10: 3500 | D10: 44579 | F10: =IF(MONTH(F$5)<MONTH($D10),$C10,IF(MONTH(F$5)=MONTH($D10),DAY($D10)/DAY(EOMONTH(F$5,0))*$C10,0)) -> 2032.2581 | G10: =IF(MONTH(G$5)<MONTH($D10),$C10,IF(MONTH(G$5)=MONTH($D10),DAY($D10)/DAY(EOMONTH(G$5,0))*$C10,0)) -> 0 | H10: =IF(MONTH(H$5)<MONTH($D10),$C10,IF(MONTH(H$5)=MONTH($D10),DAY($D10)/DAY(EOMONTH(H$5,0))*$C10,0)) -> 0 | I10: =IF(MONTH(I$5)<MONTH($D10),$C10,IF(MONTH(I$5)=MONTH($D10),DAY($D10)/DAY(EOMONTH(I$5,0))*$C10,0)) -> 0 | J10: =IF(MONTH(J$5)<MONTH($D10),$C10,IF(MONTH(J$5)=MONTH($D10),DAY($D10)/DAY(EOMONTH(J$5,0))*$C10,0)) -> 0 | K10: =IF(MONTH(K$5)<MONTH($D10),$C10,IF(MONTH(K$5)=MONTH($D10),DAY($D10)/DAY(EOMONTH(K$5,0))*$C10,0)) -> 0 | L10: =IF(MONTH(L$5)<MONTH($D10),$C10,IF(MONTH(L$5)=MONTH($D10),DAY($D10)/DAY(EOMONTH(L$5,0))*$C10,0)) -> 0 | M10: =IF(MONTH(M$5)<MONTH($D10),$C10,IF(MONTH(M$5)=MONTH($D10),DAY($D10)/DAY(EOMONTH(M$5,0))*$C10,0)) -> 0 | ... Q10: =IF(MONTH(Q$5)<MONTH($D10),$C10,IF(MONTH(Q$5)=MONTH($D10),DAY($D10)/DAY(EOMONTH(Q$5,0))*$C10,0)) -> 0
